dragonglass/__init__.py
dragonglass/cli.py
dragonglass/main.py
dragonglass/utils.py
dragonglass/core/__init__.py
dragonglass/core/config.py
dragonglass/core/models.py
dragonglass/core/protocols.py
dragonglass/core/rag.py
dragonglass/infra/__init__.py
dragonglass/infra/db.py
dragonglass/infra/providers/__init__.py
dragonglass/infra/providers/gemini.py
dragonglass-0.1.0b4.dist-info/METADATA
dragonglass-0.1.0b4.dist-info/WHEEL
dragonglass-0.1.0b4.dist-info/entry_points.txt
dragonglass-0.1.0b4.dist-info/licenses/LICENSE
dragonglass-0.1.0b4.dist-info/RECORD
