Metadata-Version: 2.4
Name: dragonglass
Version: 0.1.0b4
Summary: LLM CLI engineered for developer workflows. Built on Hexagonal Architecture** for strict typing, modularity, and speed
Author-email: Saadman Rafat <saadman@outlook.com>
License-File: LICENSE
Keywords: ai,gemini,genai,generative-ai,google,llm,vertex-ai
Classifier: Development Status :: 4 - Beta
Classifier: Intended Audience :: Developers
Classifier: License :: OSI Approved :: MIT License
Classifier: Programming Language :: Python :: 3.10
Classifier: Programming Language :: Python :: 3.11
Classifier: Programming Language :: Python :: 3.12
Classifier: Programming Language :: Python :: 3.13
Classifier: Programming Language :: Python :: 3.14
Classifier: Topic :: Software Development :: Libraries :: Python Modules
Requires-Python: >=3.10
Requires-Dist: chromadb>=1.3.5
Requires-Dist: google-genai>=1.52.0
Requires-Dist: hatchling>=1.28.0
Requires-Dist: platformdirs>=4.5.0
Requires-Dist: pydantic-settings>=2.12.0
Requires-Dist: pydantic>=2.12.5
Requires-Dist: rich>=14.2.0
Requires-Dist: sqlmodel>=0.0.27
Requires-Dist: typer>=0.20.0
